CHANGES.txt
MANIFEST.in
README.txt
TODO.txt
setup.py
src/isodate/__init__.py
src/isodate/duration.py
src/isodate/isodates.py
src/isodate/isodatetime.py
src/isodate/isoduration.py
src/isodate/isoerror.py
src/isodate/isostrf.py
src/isodate/isotime.py
src/isodate/isotzinfo.py
src/isodate/tzinfo.py
src/isodate.egg-info/PKG-INFO
src/isodate.egg-info/SOURCES.txt
src/isodate.egg-info/dependency_links.txt
src/isodate.egg-info/top_level.txt
src/isodate/tests/__init__.py
src/isodate/tests/test_date.py
src/isodate/tests/test_datetime.py
src/isodate/tests/test_duration.py
src/isodate/tests/test_time.py