Metadata-Version: 1.0
Name: isodate
Version: 0.4.6
Summary: An ISO 8601 date/time/duration parser and formater
Home-page: http://cheeseshop.python.org/pypi/isodate
Author: Gerhard Weis
Author-email: gerhard.weis@proclos.com
License: BSD
Platform: UNKNOWN
Classifier: Development Status :: 4 - Beta
Classifier: Intended Audience :: Developers
Classifier: License :: OSI Approved :: BSD License
Classifier: Operating System :: OS Independent
Classifier: Programming Language :: Python
Classifier: Programming Language :: Python :: 2
Classifier: Programming Language :: Python :: 3
Classifier: Topic :: Internet
Classifier: Topic :: Software Development :: Libraries :: Python Modules
